bin2vid/__init__.py
bin2vid-0.0.1.dist-info/DESCRIPTION.rst
bin2vid-0.0.1.dist-info/METADATA
bin2vid-0.0.1.dist-info/RECORD
bin2vid-0.0.1.dist-info/WHEEL
bin2vid-0.0.1.dist-info/metadata.json
bin2vid-0.0.1.dist-info/top_level.txt
