Metadata-Version: 2.0
Name: bin2vid
Version: 0.0.1
Summary: Full workflow pipeline from vinyl in a bin to audio files / video files
Home-page: https://github.com/MartinBarker/vinyl2digital
Author: Martin Barker
Author-email: martinbarker99@gmail.com
License: UNKNOWN
Platform: UNKNOWN
Classifier: Programming Language :: Python :: 3
Classifier: License :: OSI Approved :: MIT License
Classifier: Operating System :: OS Independent
Requires-Python: >=3.6
Requires-Dist: mutagen
Requires-Dist: requests
